{"areas":[{"0":"10775","areaid":"10775","1":"\u5fb7\u4ee4\u54c8","areaname":"\u5fb7\u4ee4\u54c8","2":"242","cityid":"242","3":"1","displayorder":"1","4":"97.36744","longitude":"97.36744","5":"37.37532","latitude":"37.37532"},{"0":"10776","areaid":"10776","1":"\u683c\u5c14\u6728","areaname":"\u683c\u5c14\u6728","2":"242","cityid":"242","3":"2","displayorder":"2","4":"94.90975","longitude":"94.90975","5":"36.40859","latitude":"36.40859"},{"0":"10777","areaid":"10777","1":"\u4e4c\u5170","areaname":"\u4e4c\u5170","2":"242","cityid":"242","3":"3","displayorder":"3","4":"98.48657","longitude":"98.48657","5":"36.93561","latitude":"36.93561"},{"0":"10778","areaid":"10778","1":"\u90fd\u5170","areaname":"\u90fd\u5170","2":"242","cityid":"242","3":"4","displayorder":"4","4":"98.10191","longitude":"98.10191","5":"36.30957","latitude":"36.30957"},{"0":"10779","areaid":"10779","1":"\u5929\u5cfb","areaname":"\u5929\u5cfb","2":"242","cityid":"242","3":"5","displayorder":"5","4":"98.49651","longitude":"98.49651","5":"38.05175","latitude":"38.05175"},{"0":"10780","areaid":"10780","1":"\u51b7\u6e56\u884c\u59d4","areaname":"\u51b7\u6e56\u884c\u59d4","2":"242","cityid":"242","3":"6","displayorder":"6","4":"93.34164","longitude":"93.34164","5":"38.88142","latitude":"38.88142"},{"0":"10781","areaid":"10781","1":"\u5927\u67f4\u65e6\u884c\u59d4","areaname":"\u5927\u67f4\u65e6\u884c\u59d4","2":"242","cityid":"242","3":"7","displayorder":"7","4":"95.36112","longitude":"95.36112","5":"37.86176","latitude":"37.86176"},{"0":"10782","areaid":"10782","1":"\u832b\u5d16\u884c\u59d4","areaname":"\u832b\u5d16\u884c\u59d4","2":"242","cityid":"242","3":"8","displayorder":"8","4":"90.86349","longitude":"90.86349","5":"38.25622","latitude":"38.25622"}]}