{"areas":[{"0":"10361","areaid":"10361","1":"\u4ead\u6e56","areaname":"\u4ead\u6e56","2":"189","cityid":"189","3":"1","displayorder":"1","4":"120.20189","longitude":"120.20189","5":"33.39468","latitude":"33.39468"},{"0":"10362","areaid":"10362","1":"\u76d0\u90fd","areaname":"\u76d0\u90fd","2":"189","cityid":"189","3":"2","displayorder":"2","4":"120.16099","longitude":"120.16099","5":"33.34323","latitude":"33.34323"},{"0":"10363","areaid":"10363","1":"\u5927\u4e30","areaname":"\u5927\u4e30","2":"189","cityid":"189","3":"3","displayorder":"3","4":"120.50746","longitude":"120.50746","5":"33.20723","latitude":"33.20723"},{"0":"10364","areaid":"10364","1":"\u4e1c\u53f0","areaname":"\u4e1c\u53f0","2":"189","cityid":"189","3":"4","displayorder":"4","4":"120.32704","longitude":"120.32704","5":"32.87278","latitude":"32.87278"},{"0":"10365","areaid":"10365","1":"\u961c\u5b81","areaname":"\u961c\u5b81","2":"189","cityid":"189","3":"5","displayorder":"5","4":"119.80916","longitude":"119.80916","5":"33.76510","latitude":"33.76510"},{"0":"10366","areaid":"10366","1":"\u5efa\u6e56","areaname":"\u5efa\u6e56","2":"189","cityid":"189","3":"6","displayorder":"6","4":"119.80511","longitude":"119.80511","5":"33.46990","latitude":"33.46990"},{"0":"10367","areaid":"10367","1":"\u5c04\u9633","areaname":"\u5c04\u9633","2":"189","cityid":"189","3":"7","displayorder":"7","4":"120.26460","longitude":"120.26460","5":"33.78117","latitude":"33.78117"},{"0":"10368","areaid":"10368","1":"\u6ee8\u6d77","areaname":"\u6ee8\u6d77","2":"189","cityid":"189","3":"8","displayorder":"8","4":"119.82726","longitude":"119.82726","5":"33.99540","latitude":"33.99540"},{"0":"10369","areaid":"10369","1":"\u54cd\u6c34","areaname":"\u54cd\u6c34","2":"189","cityid":"189","3":"9","displayorder":"9","4":"119.58499","longitude":"119.58499","5":"34.20483","latitude":"34.20483"},{"0":"10370","areaid":"10370","1":"\u5176\u4ed6","areaname":"\u5176\u4ed6","2":"189","cityid":"189","3":"10","displayorder":"10","4":"120.17725","longitude":"120.17725","5":"33.31800","latitude":"33.31800"}]}