{"areas":[{"0":"10472","areaid":"10472","1":"\u5409\u5dde","areaname":"\u5409\u5dde","2":"201","cityid":"201","3":"1","displayorder":"1","4":"115.00111","longitude":"115.00111","5":"27.15072","latitude":"27.15072"},{"0":"10473","areaid":"10473","1":"\u9752\u539f","areaname":"\u9752\u539f","2":"201","cityid":"201","3":"2","displayorder":"2","4":"115.02121","longitude":"115.02121","5":"27.08761","latitude":"27.08761"},{"0":"10474","areaid":"10474","1":"\u4e95\u5188\u5c71","areaname":"\u4e95\u5188\u5c71","2":"201","cityid":"201","3":"3","displayorder":"3","4":"114.17129","longitude":"114.17129","5":"26.58321","latitude":"26.58321"},{"0":"10475","areaid":"10475","1":"\u9042\u5ddd","areaname":"\u9042\u5ddd","2":"201","cityid":"201","3":"4","displayorder":"4","4":"114.52708","longitude":"114.52708","5":"26.31945","latitude":"26.31945"},{"0":"10476","areaid":"10476","1":"\u5409\u5b89\u53bf","areaname":"\u5409\u5b89\u53bf","2":"201","cityid":"201","3":"5","displayorder":"5","4":"114.91480","longitude":"114.91480","5":"27.04504","latitude":"27.04504"},{"0":"10477","areaid":"10477","1":"\u5409\u6c34","areaname":"\u5409\u6c34","2":"201","cityid":"201","3":"6","displayorder":"6","4":"115.14207","longitude":"115.14207","5":"27.23542","latitude":"27.23542"},{"0":"10478","areaid":"10478","1":"\u5ce1\u6c5f","areaname":"\u5ce1\u6c5f","2":"201","cityid":"201","3":"7","displayorder":"7","4":"115.32283","longitude":"115.32283","5":"27.58923","latitude":"27.58923"},{"0":"10479","areaid":"10479","1":"\u65b0\u5e72","areaname":"\u65b0\u5e72","2":"201","cityid":"201","3":"8","displayorder":"8","4":"115.39352","longitude":"115.39352","5":"27.74584","latitude":"27.74584"},{"0":"10480","areaid":"10480","1":"\u6c38\u4e30","areaname":"\u6c38\u4e30","2":"201","cityid":"201","3":"9","displayorder":"9","4":"115.44829","longitude":"115.44829","5":"27.32449","latitude":"27.32449"},{"0":"10481","areaid":"10481","1":"\u6cf0\u548c","areaname":"\u6cf0\u548c","2":"201","cityid":"201","3":"10","displayorder":"10","4":"114.91546","longitude":"114.91546","5":"26.79563","latitude":"26.79563"},{"0":"10482","areaid":"10482","1":"\u4e07\u5b89","areaname":"\u4e07\u5b89","2":"201","cityid":"201","3":"11","displayorder":"11","4":"114.79273","longitude":"114.79273","5":"26.46392","latitude":"26.46392"},{"0":"10483","areaid":"10483","1":"\u5b89\u798f","areaname":"\u5b89\u798f","2":"201","cityid":"201","3":"12","displayorder":"12","4":"114.62608","longitude":"114.62608","5":"27.39898","latitude":"27.39898"},{"0":"10484","areaid":"10484","1":"\u6c38\u65b0","areaname":"\u6c38\u65b0","2":"201","cityid":"201","3":"13","displayorder":"13","4":"114.24949","longitude":"114.24949","5":"26.95132","latitude":"26.95132"},{"0":"10485","areaid":"10485","1":"\u5e90\u9675\u65b0\u533a","areaname":"\u5e90\u9675\u65b0\u533a","2":"201","cityid":"201","3":"14","displayorder":"14","4":"114.97326","longitude":"114.97326","5":"27.09779","latitude":"27.09779"}]}