{"areas":[{"0":"1083","areaid":"1083","1":"\u6dc7\u6ee8","areaname":"\u6dc7\u6ee8","2":"120","cityid":"120","3":"1","displayorder":"1","4":"114.30531","longitude":"114.30531","5":"35.74695","latitude":"35.74695"},{"0":"1084","areaid":"1084","1":"\u5c71\u57ce","areaname":"\u5c71\u57ce","2":"120","cityid":"120","3":"2","displayorder":"2","4":"114.19106","longitude":"114.19106","5":"35.90332","latitude":"35.90332"},{"0":"1085","areaid":"1085","1":"\u9e64\u5c71","areaname":"\u9e64\u5c71","2":"120","cityid":"120","3":"3","displayorder":"3","4":"114.16986","longitude":"114.16986","5":"35.96048","latitude":"35.96048"},{"0":"1086","areaid":"1086","1":"\u6d5a\u53bf","areaname":"\u6d5a\u53bf","2":"120","cityid":"120","3":"4","displayorder":"4","4":"114.55739","longitude":"114.55739","5":"35.68188","latitude":"35.68188"},{"0":"1087","areaid":"1087","1":"\u6dc7\u53bf","areaname":"\u6dc7\u53bf","2":"120","cityid":"120","3":"5","displayorder":"5","4":"114.20421","longitude":"114.20421","5":"35.61365","latitude":"35.61365"}]}