{"areas":[{"0":"11511","areaid":"11511","1":"\u4f0a\u5b81\u5e02","areaname":"\u4f0a\u5b81\u5e02","2":"319","cityid":"319","3":"1","displayorder":"1","4":"81.28379","longitude":"81.28379","5":"43.91541","latitude":"43.91541"},{"0":"11512","areaid":"11512","1":"\u594e\u5c6f","areaname":"\u594e\u5c6f","2":"319","cityid":"319","3":"2","displayorder":"2","4":"84.90832","longitude":"84.90832","5":"44.43265","latitude":"44.43265"},{"0":"11513","areaid":"11513","1":"\u970d\u57ce","areaname":"\u970d\u57ce","2":"319","cityid":"319","3":"3","displayorder":"3","4":"80.78116","longitude":"80.78116","5":"44.30912","latitude":"44.30912"},{"0":"11514","areaid":"11514","1":"\u5de9\u7559","areaname":"\u5de9\u7559","2":"319","cityid":"319","3":"4","displayorder":"4","4":"82.44570","longitude":"82.44570","5":"43.30246","latitude":"43.30246"},{"0":"11515","areaid":"11515","1":"\u65b0\u6e90","areaname":"\u65b0\u6e90","2":"319","cityid":"319","3":"5","displayorder":"5","4":"83.55815","longitude":"83.55815","5":"43.37695","latitude":"43.37695"},{"0":"11516","areaid":"11516","1":"\u662d\u82cf","areaname":"\u662d\u82cf","2":"319","cityid":"319","3":"6","displayorder":"6","4":"80.98426","longitude":"80.98426","5":"42.77688","latitude":"42.77688"},{"0":"11517","areaid":"11517","1":"\u7279\u514b\u65af","areaname":"\u7279\u514b\u65af","2":"319","cityid":"319","3":"7","displayorder":"7","4":"82.00685","longitude":"82.00685","5":"42.92556","latitude":"42.92556"},{"0":"11518","areaid":"11518","1":"\u5c3c\u52d2\u514b","areaname":"\u5c3c\u52d2\u514b","2":"319","cityid":"319","3":"8","displayorder":"8","4":"83.23110","longitude":"83.23110","5":"43.81673","latitude":"43.81673"},{"0":"11519","areaid":"11519","1":"\u5bdf\u5e03\u67e5\u5c14","areaname":"\u5bdf\u5e03\u67e5\u5c14","2":"319","cityid":"319","3":"9","displayorder":"9","4":null,"longitude":null,"5":null,"latitude":null},{"0":"11520","areaid":"11520","1":"\u4f0a\u5b81\u53bf","areaname":"\u4f0a\u5b81\u53bf","2":"319","cityid":"319","3":"10","displayorder":"10","4":"81.53393","longitude":"81.53393","5":"43.98296","latitude":"43.98296"}]}